FlaskAPIServer/__init__.py
FlaskAPIServer/config.py
FlaskAPIServer/extensions.py
FlaskAPIServer/middleware.py
FlaskAPIServer/server.py
FlaskAPIServer/routes/__init__.py
FlaskAPIServer/routes/key_roles.py
FlaskAPIServer/routes/keys.py
FlaskAPIServer/utils/__init__.py
FlaskAPIServer/utils/database.py
FlaskAPIServer/utils/logger.py
FlaskAPIServer/utils/mail.py
FlaskAPIServer/utils/utils.py
flaskapiserver-0.2.1.1.dist-info/licenses/LICENSE
flaskapiserver-0.2.1.1.dist-info/METADATA
flaskapiserver-0.2.1.1.dist-info/WHEEL
flaskapiserver-0.2.1.1.dist-info/top_level.txt
flaskapiserver-0.2.1.1.dist-info/RECORD
